{"stats":{"minecraft:custom":{"minecraft:sprint_one_cm":3262,"minecraft:time_since_rest":5962,"minecraft:walk_one_cm":715,"minecraft:total_world_time":5962,"minecraft:fly_one_cm":2171,"minecraft:crouch_one_cm":27,"minecraft:sneak_time":17,"minecraft:play_time":5962,"minecraft:jump":11,"minecraft:time_since_death":5962},"minecraft:picked_up":{"minecraft:cobblestone":13,"minecraft:granite":288,"minecraft:cobbled_deepslate":27,"minecraft:andesite":15},"minecraft:used":{"minecraft:repeating_command_block":2,"minecraft:chain_command_block":1}},"DataVersion":4440}